{
	"Name" : "Cave_spikes",
	"Signature" : "00000000000000000000000000000011",
	"Sprite" : 
	{
		"AnimationIndex" : 0,
		"Layer" : 1,
		"SpriteColorA" : 1.0,
		"SpriteColorX" : 1.0,
		"SpriteColorY" : 1.0,
		"SpriteColorZ" : 1.0,
		"SpriteCurrentTexIndex" : 0,
		"SpriteFilename" : "Cave_spikes.png",
		"SpriteName" : "Quad",
		"SpritePrimitiveType" : 5,
		"SpriteTexture" : 14,
		"SpriteTextureHeight" : 857,
		"SpriteTextureIndex" : 13,
		"SpriteTextureWidth" : 657,
		"SpriteTransformRotation" : 0.0,
		"SpriteTransformScalingX" : 170.81999206542969,
		"SpriteTransformScalingY" : 222.81999206542969,
		"SpriteTransformWorldPositionX" : 154.5728759765625,
		"SpriteTransformWorldPositionY" : 422.28912353515625,
		"animations" : []
	},
	"Transform" : 
	{
		"TransformRotation" : 0.0,
		"TransformScalingX" : 170.81999206542969,
		"TransformScalingY" : 222.81999206542969,
		"TransformWorldPositionX" : 154.5728759765625,
		"TransformWorldPositionY" : 422.28912353515625
	}
}